{
  "language": "en",
  "segments": [
    {
      "id": 1,
      "start": 0.0,
      "end": 7.54,
      "text": "Don't even think that you should have any fear or the members of this party should have any fear.",
      "language": "en",
      "style": "clean"
    },
    {
      "id": 2,
      "start": 8.52,
      "end": 11.4,
      "text": "God willing, we will handle all of them.",
      "language": "en",
      "style": "clean"
    },
    {
      "id": 3,
      "start": 11.64,
      "end": 13.24,
      "text": "All of them are alone.",
      "language": "en",
      "style": "clean"
    },
    {
      "id": 4,
      "start": 13.24,
      "end": 15.06,
      "text": "How long have you lived?",
      "language": "en",
      "style": "clean"
    },
    {
      "id": 5,
      "start": 15.56,
      "end": 17.54,
      "text": "Your age is 64 years.",
      "language": "en",
      "style": "clean"
    },
    {
      "id": 6,
      "start": 18.42,
      "end": 22.56,
      "text": "Whether I live 80 years or 70 years, my husband knows that.",
      "language": "en",
      "style": "clean"
    },
    {
      "id": 7,
      "start": 22.56,
      "end": 31.16,
      "text": "So as long as I am alive, I would like to thank the parliament and all the new friends who have come to our parliament.",
      "language": "en",
      "style": "clean"
    }
  ],
  "word_timestamps": true,
  "confidence": 0.95,
  "source": "whisper"
}